<?xml version="1.0" encoding="utf-8"?>
<Level width="20" height="20">
	<Field x="1" y="1" type="6" width="20" length="1" />
	<Field x="1" y="2" type="6" width="1" length="18" />
	<Field x="1" y="20" type="6" width="20" length="1" />
	<Field x="2" y="2" type="10" width="17" length="1" />
	<Field x="2" y="3" type="10" width="18" length="1" />
	<Field x="2" y="4" type="10" width="18" length="1" />
	<Field x="2" y="5" type="10" width="18" length="1" />
	<Field x="2" y="6" type="10" width="5" length="1" />
	<Field x="2" y="7" type="10" width="4" length="1" />
	<Field x="2" y="8" type="10" width="5" length="1" />
	<Field x="2" y="9" type="10" width="4" length="1" />
	<Field x="2" y="10" type="10" width="5" length="1" />
	<Field x="2" y="11" type="10" width="4" length="1" />
	<Field x="2" y="12" type="10" width="5" length="1" />
	<Field x="2" y="13" type="10" width="4" length="1" />
	<Field x="2" y="14" type="10" width="5" length="1" />
	<Field x="2" y="15" type="10" width="4" length="1" />
	<Field x="2" y="16" type="10" width="18" length="1" />
	<Field x="2" y="17" type="10" width="18" length="1" />
	<Field x="2" y="18" type="10" width="18" length="1" />
	<Field x="2" y="19" type="2" width="1" length="1" />
	<Field x="3" y="19" type="10" width="17" length="1" />
	<Field x="6" y="7" type="6" width="9" length="1" />
	<Field x="6" y="9" type="6" width="9" length="1" />
	<Field x="6" y="11" type="6" width="9" length="1" />
	<Field x="6" y="13" type="6" width="9" length="1" />
	<Field x="6" y="15" type="6" width="1" length="1" />
	<Field x="7" y="6" type="6" width="1" length="1" />
	<Field x="7" y="8" type="6" width="9" length="1" />
	<Field x="7" y="10" type="6" width="9" length="1" />
	<Field x="7" y="12" type="6" width="9" length="1" />
	<Field x="7" y="14" type="6" width="9" length="1" />
	<Field x="7" y="15" type="10" width="1" length="1" />
	<Field x="8" y="6" type="10" width="1" length="1" />
	<Field x="8" y="15" type="6" width="1" length="1" />
	<Field x="9" y="6" type="6" width="1" length="1" />
	<Field x="9" y="15" type="10" width="1" length="1" />
	<Field x="10" y="6" type="10" width="1" length="1" />
	<Field x="10" y="15" type="6" width="1" length="1" />
	<Field x="11" y="6" type="6" width="1" length="1" />
	<Field x="11" y="15" type="10" width="1" length="1" />
	<Field x="12" y="6" type="10" width="1" length="1" />
	<Field x="12" y="15" type="6" width="1" length="1" />
	<Field x="13" y="6" type="6" width="1" length="1" />
	<Field x="13" y="15" type="10" width="1" length="1" />
	<Field x="14" y="6" type="10" width="1" length="1" />
	<Field x="14" y="15" type="6" width="1" length="1" />
	<Field x="15" y="6" type="6" width="1" length="1" />
	<Field x="15" y="7" type="10" width="5" length="1" />
	<Field x="15" y="9" type="10" width="5" length="1" />
	<Field x="15" y="11" type="10" width="5" length="1" />
	<Field x="15" y="13" type="10" width="5" length="1" />
	<Field x="15" y="15" type="10" width="5" length="1" />
	<Field x="16" y="6" type="10" width="4" length="1" />
	<Field x="16" y="8" type="10" width="4" length="1" />
	<Field x="16" y="10" type="10" width="4" length="1" />
	<Field x="16" y="12" type="10" width="4" length="1" />
	<Field x="16" y="14" type="10" width="4" length="1" />
	<Field x="19" y="2" type="1" width="1" length="1" />
	<Field x="20" y="2" type="6" width="1" length="18" />
</Level>